[{
	"fileName": "1.png",
	"title": "Ture Love Story",
	"desc": "Let's go to the history!"
}, {
	"fileName": "2.png",
	"title": "Ture Love Story",
	"desc": "Let's go to the history!"
}, {
	"fileName": "3.png",
	"title": "Ture Love Story",
	"desc": "Let's go to the history!"
}, {
	"fileName": "4.png",
	"title": "Ture Love Story",
	"desc": "Let's go to the history!"
}, {
	"fileName": "5.png",
	"title": "Ture Love Story",
	"desc": "Let's go to the history!"
}, {
	"fileName": "6.png",
	"title": "Ture Love Story",
	"desc": "Let's go to the history!"
}, {
	"fileName": "7.png",
	"title": "Ture Love Story",
	"desc": "Let's go to the history!"
}, {
	"fileName": "8.png",
	"title": "Ture Love Story",
	"desc": "Let's go to the history!"
}, {
	"fileName": "9.png",
	"title": "Ture Love Story",
	"desc": "Let's go to the history!"
}, {
	"fileName": "10.png",
	"title": "Ture Love Story",
	"desc": "Let's go to the history!"
}, {
	"fileName": "11.png",
	"title": "Ture Love Story",
	"desc": "Let's go to the history!"
}, {
	"fileName": "12.png",
	"title": "Ture Love Story",
	"desc": "Let's go to the history!"
}]